{"name":"HOLA","id":"hola;hola","testSteps":[{"number":1,"description":"Given karina","duration":3,"startTime":"2022-04-07T12:39:11.001-05:00[America/Bogota]","result":"PENDING","precondition":false},{"number":2,"description":"When saluda","duration":0,"startTime":"2022-04-07T12:39:11.009-05:00[America/Bogota]","result":"PENDING","precondition":false},{"number":3,"description":"Then hoy","duration":1,"startTime":"2022-04-07T12:39:11.009-05:00[America/Bogota]","result":"PENDING","precondition":false}],"userStory":{"id":"hola","storyName":"hola","path":"src/test/resources/features/bancolombia.feature","type":"feature"},"featureTag":{"name":"Features/hola","type":"feature"},"title":"HOLA","tags":[{"name":"Hola","type":"feature"},{"name":"stories","type":"tag"}],"startTime":"2022-04-07T12:39:10.733-05:00[America/Bogota]","duration":309,"projectKey":"","annotatedResult":"PENDING","manual":false,"testSource":"Cucumber","result":"PENDING"}